{
    "Id": "bastion_constructor",
    "DisplayName": "Constructor",
    "FactionId": "bastion",
    "Category": "HeavyVehicle",
    "MovementClassId": "HeavyVehicle",
    "MaxHealth": 380.0,
    "ArmorValue": 4.0,
    "ArmorClass": "Heavy",
    "SightRange": 7.0,
    "BuildTime": 18.0,
    "Cost": 1000,
    "SecondaryCost": 50,
    "PopulationCost": 2,
    "Weapons": [],
    "SpecialAbilityId": "build_anywhere",
    "Description": "Bastion's expansion vehicle \u2014 where the Constructor goes, the fortress follows.",
    "SpeedOverride": 0.06,
    "TurnRateOverride": null,
    "MassOverride": null,
    "FootprintWidth": 3,
    "FootprintHeight": 3,
    "CanGarrison": false,
    "CanCrush": false,
    "IsStealthed": false,
    "IsDetector": false
}