{
  "Id": "arcloft_barracks",
  "DisplayName": "Sentinel Barracks",
  "FactionId": "arcloft",
  "Category": "Production",
  "MaxHealth": 1000,
  "ArmorClass": "Building",
  "ArmorValue": 5,
  "Cost": 800,
  "SecondaryCost": 0,
  "BuildTime": 20.0,
  "FootprintWidth": 3,
  "FootprintHeight": 3,
  "PowerRequired": 0,
  "PowerGenerated": 0,
  "SupplyProvided": 0,
  "PassiveIncome": 0,
  "VCGeneration": 0,
  "Abilities": [
    "produce_infantry"
  ],
  "Prerequisites": [
    "arcloft_refinery"
  ],
  "Description": "Trains Arcloft sentinel infantry, EMP specialists, and drone operators."
}